segmentation_forests/__init__.py
segmentation_forests/divergence.py
segmentation_forests/forest.py
segmentation_forests/node.py
segmentation_forests/py.typed
segmentation_forests/tree.py
segmentation_forests/visualization.py
segmentation_forests-0.1.0.dist-info/licenses/LICENSE
segmentation_forests-0.1.0.dist-info/METADATA
segmentation_forests-0.1.0.dist-info/WHEEL
segmentation_forests-0.1.0.dist-info/top_level.txt
segmentation_forests-0.1.0.dist-info/RECORD
