Metadata-Version: 2.4
Name: segmentation-forests
Version: 0.1.0
Summary: Unsupervised segment discovery using divergence-based decision trees inspired by Random Forests
Author-email: David Williams <david@davidgeorgewilliams.com>
License-Expression: MIT
Project-URL: Homepage, https://github.com/davidgeorgewilliams/segmentation-forests
Project-URL: Documentation, https://github.com/davidgeorgewilliams/segmentation-forests/blob/main/README.md
Project-URL: Repository, https://github.com/davidgeorgewilliams/segmentation-forests
Project-URL: Bug Tracker, https://github.com/davidgeorgewilliams/segmentation-forests/issues
Keywords: machine-learning,unsupervised-learning,segment-discovery,data-mining,random-forests
Classifier: Intended Audience :: Science/Research
Classifier: Intended Audience :: Developers
Classifier: Topic :: Scientific/Engineering :: Artificial Intelligence
Classifier: Topic :: Scientific/Engineering :: Information Analysis
Classifier: Programming Language :: Python :: 3.12
Requires-Python: >=3.12
License-File: LICENSE
Requires-Dist: numpy>=1.20.0
Requires-Dist: pandas>=1.3.0
Requires-Dist: scipy>=1.7.0
Requires-Dist: matplotlib>=3.4.0
Requires-Dist: seaborn>=0.11.0
Provides-Extra: dev
Requires-Dist: pytest>=7.4.0; extra == "dev"
Requires-Dist: pytest-cov>=4.1.0; extra == "dev"
Requires-Dist: pytest-mock>=3.11.0; extra == "dev"
Requires-Dist: black>=23.0.0; extra == "dev"
Requires-Dist: ruff>=0.1.0; extra == "dev"
Requires-Dist: mypy>=1.5.0; extra == "dev"
Requires-Dist: isort>=5.12.0; extra == "dev"
Requires-Dist: pre-commit>=4.2.0; extra == "dev"
Requires-Dist: jupyter>=1.0.0; extra == "dev"
Requires-Dist: ipython>=8.14.0; extra == "dev"
Provides-Extra: test
Requires-Dist: pytest>=7.4.0; extra == "test"
Requires-Dist: pytest-cov>=4.1.0; extra == "test"
Requires-Dist: pytest-mock>=3.12.0; extra == "test"
Dynamic: license-file
